README.txt
setup.cfg
setup.py
Products/__init__.py
Products.Quota.egg-info/PKG-INFO
Products.Quota.egg-info/SOURCES.txt
Products.Quota.egg-info/dependency_links.txt
Products.Quota.egg-info/entry_points.txt
Products.Quota.egg-info/namespace_packages.txt
Products.Quota.egg-info/not-zip-safe
Products.Quota.egg-info/requires.txt
Products.Quota.egg-info/top_level.txt
Products/Quota/CREDITS.txt
Products/Quota/INSTALL.txt
Products/Quota/LICENSE.GPL
Products/Quota/LICENSE.txt
Products/Quota/README.txt
Products/Quota/TODO.txt
Products/Quota/__init__.py
Products/Quota/adapters.py
Products/Quota/config.py
Products/Quota/configure.zcml
Products/Quota/handlers.py
Products/Quota/interfaces.py
Products/Quota/quotaservice.py
Products/Quota/settings.py
Products/Quota/tool.gif
Products/Quota/browser/__init__.py
Products/Quota/browser/configure.zcml
Products/Quota/browser/portlet.pt
Products/Quota/browser/portlet.py
Products/Quota/browser/qf_icon.gif
Products/Quota/browser/quota.pt
Products/Quota/browser/quotaview.py
Products/Quota/browser/settings_controlpanel.py
Products/Quota/content/__init__.py
Products/Quota/content/quotafolder.py
Products/Quota/exportimport/__init__.py
Products/Quota/exportimport/install.py
Products/Quota/i18n/quota-de.po
Products/Quota/i18n/quota-es.po
Products/Quota/i18n/quota-it.po
Products/Quota/i18n/quota-nl.po
Products/Quota/i18n/quota.pot
Products/Quota/profiles/default/actionicons.xml
Products/Quota/profiles/default/catalog.xml
Products/Quota/profiles/default/componentregistry.xml
Products/Quota/profiles/default/controlpanel.xml
Products/Quota/profiles/default/factorytool.xml
Products/Quota/profiles/default/import_steps.xml
Products/Quota/profiles/default/install_quota.txt
Products/Quota/profiles/default/metadata.xml
Products/Quota/profiles/default/portlets.xml
Products/Quota/profiles/default/rolemap.xml
Products/Quota/profiles/default/types.xml
Products/Quota/profiles/default/types/QuotaFolder.xml
Products/Quota/tests/__init__.py
Products/Quota/tests/test_quota.py
Products/Quota/tests/input/Barracuda.jpg
Products/Quota/tests/input/img.gif
docs/HISTORY.txt