Metadata-Version: 1.0
Name: Products.Quota
Version: 0.2
Summary: Adds a folder type with a size limit to your Plone site.
Home-page: http://plone.org/products/Products.Quota
Author: Enrique Peréz
Author-email: eperez@yaco.es
License: GPL
Keywords: plone quota
Platform: UNKNOWN
Classifier: Programming Language :: Python
